SpringDataElasticsearchZhongwenWendang/README.md
SpringDataElasticsearchZhongwenWendang/__init__.py
SpringDataElasticsearchZhongwenWendang/__main__.py
SpringDataElasticsearchZhongwenWendang/file.epub
SpringDataElasticsearchZhongwenWendang/index.html
SpringDataElasticsearchZhongwenWendang/css/__init__.py
SpringDataElasticsearchZhongwenWendang/css/annotations.css
SpringDataElasticsearchZhongwenWendang/css/main.css
SpringDataElasticsearchZhongwenWendang/css/normalize.css
SpringDataElasticsearchZhongwenWendang/css/popup.css
SpringDataElasticsearchZhongwenWendang/font/__init__.py
SpringDataElasticsearchZhongwenWendang/font/fontello.eot
SpringDataElasticsearchZhongwenWendang/font/fontello.svg
SpringDataElasticsearchZhongwenWendang/font/fontello.ttf
SpringDataElasticsearchZhongwenWendang/font/fontello.woff
SpringDataElasticsearchZhongwenWendang/img/__init__.py
SpringDataElasticsearchZhongwenWendang/img/annotator-glyph-sprite.png
SpringDataElasticsearchZhongwenWendang/img/annotator-icon-sprite.png
SpringDataElasticsearchZhongwenWendang/img/apple-touch-icon.png
SpringDataElasticsearchZhongwenWendang/img/cancelfullscreen.png
SpringDataElasticsearchZhongwenWendang/img/close.png
SpringDataElasticsearchZhongwenWendang/img/fullscreen.png
SpringDataElasticsearchZhongwenWendang/img/loader.gif
SpringDataElasticsearchZhongwenWendang/img/menu-icon.png
SpringDataElasticsearchZhongwenWendang/img/save.png
SpringDataElasticsearchZhongwenWendang/img/saved.png
SpringDataElasticsearchZhongwenWendang/img/settings-s.png
SpringDataElasticsearchZhongwenWendang/img/settings.png
SpringDataElasticsearchZhongwenWendang/img/star.png
SpringDataElasticsearchZhongwenWendang/js/__init__.py
SpringDataElasticsearchZhongwenWendang/js/epub.js
SpringDataElasticsearchZhongwenWendang/js/epub.min.js
SpringDataElasticsearchZhongwenWendang/js/epub.min.map
SpringDataElasticsearchZhongwenWendang/js/hooks.min.js
SpringDataElasticsearchZhongwenWendang/js/hooks.min.map
spring_data_elasticsearch_zhongwen_wendang-2024.3.2.0.dist-info/METADATA
spring_data_elasticsearch_zhongwen_wendang-2024.3.2.0.dist-info/WHEEL
spring_data_elasticsearch_zhongwen_wendang-2024.3.2.0.dist-info/entry_points.txt
spring_data_elasticsearch_zhongwen_wendang-2024.3.2.0.dist-info/top_level.txt
spring_data_elasticsearch_zhongwen_wendang-2024.3.2.0.dist-info/RECORD
